reproducible_figures/__init__.py
reproducible_figures/plotting.py
reproducible_figures/utility.py
reproducible_figures/test/__init__.py
reproducible_figures/test/test_save_figure.py
reproducible_figures/test/test_utils.py
reproducible_figures-1.2.2.dist-info/LICENSE
reproducible_figures-1.2.2.dist-info/METADATA
reproducible_figures-1.2.2.dist-info/WHEEL
reproducible_figures-1.2.2.dist-info/top_level.txt
reproducible_figures-1.2.2.dist-info/RECORD
