Metadata-Version: 2.1
Name: reproducible_figures
Version: 1.2.2
Summary: Small utility for creating reproducible figures.
Home-page: https://github.com/DylanCope/reproducible_figures
Author: Dylan R. Cope
License-File: LICENSE
Requires-Dist: pandas
Requires-Dist: matplotlib
Requires-Dist: black
